xgorn_api/__init__.py
xgorn_api/api.py
xgorn_api/features/__init__.py
xgorn_api/features/ai.py
xgorn_api/features/bypass.py
xgorn_api/features/decode.py
xgorn_api/features/encode.py
xgorn_api/features/music.py
xgorn_api/features/scrape.py
xgorn_api/features/translate.py
xgorn_api-1.0.8.dist-info/LICENSE
xgorn_api-1.0.8.dist-info/METADATA
xgorn_api-1.0.8.dist-info/WHEEL
xgorn_api-1.0.8.dist-info/top_level.txt
xgorn_api-1.0.8.dist-info/RECORD
