Metadata-Version: 2.1
Name: xgorn-api
Version: 1.0.8
Summary: API Interface for api.xgorn.pp.ua
Home-page: https://github.com/X-Gorn/xgorn-api
Author: xgorn
License: MIT
Project-URL: Web, https://api.xgorn.pp.ua
Project-URL: Documentation, https://api.xgorn.pp.ua/docs
Keywords: api scraper bypasser translator client library python
Classifier: Development Status :: 5 - Production/Stable
Classifier: Intended Audience :: Developers
Classifier: Natural Language :: English
Classifier: License :: OSI Approved :: GNU Lesser General Public License v3 (LGPLv3)
Classifier: Operating System :: OS Independent
Classifier: Programming Language :: Python
Classifier: Programming Language :: Python :: 3
Classifier: Programming Language :: Python :: 3.7
Classifier: Programming Language :: Python :: 3.8
Classifier: Programming Language :: Python :: 3.9
Classifier: Programming Language :: Python :: 3.10
Classifier: Programming Language :: Python :: 3.11
Classifier: Topic :: Internet
Classifier: Topic :: Software Development :: Libraries
Classifier: Topic :: Software Development :: Libraries :: Python Modules
Requires-Python: ~=3.7
License-File: LICENSE
Requires-Dist: requests
